<?xml version="1.0" encoding="UTF-8"?>
<persistence version="2.0" xmlns="http://java.sun.com/xml/ns/persistence"
    xmlns:xsi="http://www.w3.org/2001/XMLSchema-instance" 
    xsi:schemaLocation="http://java.sun.com/xml/ns/persistence
                        http://java.sun.com/xml/ns/persistence/persistence_2_0.xsd">

  <persistence-unit name="pulsing">
    <!-- Provider needed only if multiple JPA implementation is used -->
    <provider>org.hibernate.jpa.HibernatePersistenceProvider</provider>

    <!-- 
        Automatic detection of annotated classes and XML mapping files is usually 
        only available in a Java EE application server, according to EJB 3.0 
        specification, but Hibernate also implements it in plain Java SE.
    -->
    <properties>
      <property name="javax.persistence.jdbc.driver" value="com.mysql.jdbc.Driver" />
      <property name="javax.persistence.jdbc.url" value="jdbc:mysql://localhost:3306/pulsing" />
      <property name="javax.persistence.jdbc.user" value="pulsing" />
      <property name="javax.persistence.jdbc.password" value="wsad" />

      <property name="hibernate.dialect" value="org.hibernate.dialect.MySQL5InnoDBDialect" />          
      <property name="hibernate.hbm2ddl.auto" value="create-drop" />
      <property name="hibernate.show_sql" value="true" />
      <property name="hibernate.format_sql" value="true" />
      <!-- Disable the second-level cache -->
      <property name="hibernate.cache.provider_class" value="org.hibernate.cache.NoCacheProvider" />
      
      <property name="hibernate.archive.autodetection" value="class, hbm" />
      <property name="hibernate.transaction.factory_class" value="org.hibernate.transaction.JDBCTransactionFactory"/>
      <property name="hibernate.c3p0.min_size" value="5" />
      <property name="hibernate.c3p0.max_size" value="20" />
      <property name="hibernate.c3p0.timeout" value="300" />
      <property name="hibernate.c3p0.max_statements" value="50" />
      <property name="hibernate.c3p0.idle_test_period" value="3000" />
      <property name="hibernate.id.new_generator_mappings" value="true" />
    </properties>

  </persistence-unit>
    
</persistence>